paystack_client/__init__.py
paystack_client/client.py
paystack_client/core.py
paystack_client/exceptions.py
paystack_client/endpoints/__init__.py
paystack_client/endpoints/apple_pay.py
paystack_client/endpoints/bulk_charges.py
paystack_client/endpoints/charge.py
paystack_client/endpoints/customers.py
paystack_client/endpoints/dedicated_virtual_accounts.py
paystack_client/endpoints/direct_debit.py
paystack_client/endpoints/disputes.py
paystack_client/endpoints/integration.py
paystack_client/endpoints/miscellaneous.py
paystack_client/endpoints/payment_pages.py
paystack_client/endpoints/payment_requests.py
paystack_client/endpoints/plans.py
paystack_client/endpoints/products.py
paystack_client/endpoints/refunds.py
paystack_client/endpoints/settlements.py
paystack_client/endpoints/subaccounts.py
paystack_client/endpoints/subscriptions.py
paystack_client/endpoints/terminal.py
paystack_client/endpoints/transaction_splits.py
paystack_client/endpoints/transactions.py
paystack_client/endpoints/transfers.py
paystack_client/endpoints/transfers_control.py
paystack_client/endpoints/transfers_recipients.py
paystack_client/endpoints/verification.py
paystack_client/endpoints/virtual_terminal.py
paystack_client/utils/__init__.py
paystack_client/utils/helpers.py
paystack_client/utils/validators.py
paystack_api_wrapper-1.0.0.dist-info/METADATA
paystack_api_wrapper-1.0.0.dist-info/WHEEL
paystack_api_wrapper-1.0.0.dist-info/licenses/LICENSE
paystack_api_wrapper-1.0.0.dist-info/RECORD
