Metadata-Version: 2.4
Name: paystack-api-wrapper
Version: 1.0.0
Summary: A Python wrapper for the Paystack API
Project-URL: Homepage, https://github.com/theolujay/paystack-client
Project-URL: Repository, https://github.com/theolujay/paystack-client
Project-URL: Documentation, https://paystack-client.readthedocs.io
Project-URL: Bug Tracker, https://github.com/theolujay/paystack-client/issues
Author-email: Joseph Ezekiel <theolujay@gmail.com>
Maintainer-email: Joseph Ezekiel <theolujay@gmail.com>
License: MIT
License-File: LICENSE
Keywords: api,django,fintech,nigeria,payment,paystack,python
Classifier: Development Status :: 4 - Beta
Classifier: Framework :: Django
Classifier: Intended Audience :: Developers
Classifier: License :: OSI Approved :: MIT License
Classifier: Programming Language :: Python :: 3
Classifier: Programming Language :: Python :: 3.9
Classifier: Programming Language :: Python :: 3.10
Classifier: Programming Language :: Python :: 3.11
Classifier: Programming Language :: Python :: 3.12
Classifier: Topic :: Internet :: WWW/HTTP
Classifier: Topic :: Software Development :: Libraries :: Python Modules
Requires-Python: >=3.9
Requires-Dist: pytest>=8.4.1
Requires-Dist: requests>=2.25.0
Provides-Extra: dev
Requires-Dist: black>=22.0.0; extra == 'dev'
Requires-Dist: build>=1.0.0; extra == 'dev'
Requires-Dist: mypy>=1.0.0; extra == 'dev'
Requires-Dist: pytest-cov>=4.0.0; extra == 'dev'
Requires-Dist: pytest-mock>=3.14.1; extra == 'dev'
Requires-Dist: pytest>=8.4.1; extra == 'dev'
Requires-Dist: responses>=0.25.8; extra == 'dev'
Requires-Dist: ruff>=0.1.0; extra == 'dev'
Requires-Dist: twine>=4.0.0; extra == 'dev'
Provides-Extra: test
Requires-Dist: pytest-cov>=4.0.0; extra == 'test'
Requires-Dist: pytest>=8.4.1; extra == 'test'
Requires-Dist: responses>=0.25.8; extra == 'test'
